[
  {
    "id": 1,
    "title": "Conjunto de Bijuterias Artesanais",
    "price": 49.9,
    "author": "Ana Costa",
    "description": "Peças únicas feitas à mão com miçangas, contas e metais artesanais.",
    "img": "bijuterias.jpg",
    "reviews": [
      {
        "reviewer": "Camila Ribeiro",
        "rating": 4.5,
        "reviewText": "As bijuterias são lindas e delicadas! Amei o cuidado com o envio.",
        "reviewImages": [
          "https://images.unsplash.com/photo-1583939003579-730e3918a45a?w=300&h=200&fit=crop",
          "https://images.unsplash.com/photo-1515562141207-7a88fb7ce338?w=300&h=200&fit=crop"
        ]
      },
      {
        "reviewer": "Juliana Santos",
        "rating": 5.0,
        "reviewText": "Superou minhas expectativas! A qualidade é excelente e o acabamento impecável. Já recebi vários elogios usando as peças.",
        "reviewImages": [
          "https://images.unsplash.com/photo-1596944924616-7b38e7cfac36?w=300&h=200&fit=crop"
        ]
      },
      {
        "reviewer": "Mariana Lima",
        "rating": 4.0,
        "reviewText": "Muito bonitas! Apenas o colar chegou um pouco embaçado.",
        "reviewImages": [
          "https://images.unsplash.com/photo-1583939003579-730e3918a45a?w=300&h=200&fit=crop"
        ]
      }
    ]
  },
  {
    "id": 2,
    "title": "Tigela de Cerâmica Esmaltada",
    "price": 89.0,
    "author": "João Fernandes",
    "description": "Tigela artesanal de porcelana com acabamento esmaltado em azul cobalto.",
    "img": "ceramica-e-porcelana.webp",
    "review": {
      "reviewer": "Eduardo Melo",
      "rating": 5.0,
      "reviewText": "Excelente acabamento! A tigela é ainda mais bonita ao vivo.",
      "reviewImages": [
        "https://images.unsplash.com/photo-1583939003579-730e3918a45a?w=300&h=200&fit=crop"
      ]
    }
  },
  {
    "id": 3,
    "title": "Quadro de Ilustração Botânica",
    "price": 120.0,
    "author": "Luiza Ramos",
    "description": "Ilustração em aquarela representando espécies de plantas brasileiras.",
    "img": "bijuterias.jpg",
    "review": {
      "reviewer": "Sofia Andrade",
      "rating": 4.0,
      "reviewText": "O quadro é lindo, mas a moldura veio um pouco arranhada.",
      "reviewImages": [
        "https://images.unsplash.com/photo-1603570419983-7e865b2f1f19?w=300&h=200&fit=crop"
      ]
    }
  },
  {
    "id": 4,
    "title": "Caixa Decorativa em Madeira",
    "price": 75.0,
    "author": "Carlos Nogueira",
    "description": "Caixa entalhada manualmente com madeira reciclada de demolição.",
    "img": "artesanato-em-madeira.webp",
    "review": {
      "reviewer": "Lucas Dias",
      "rating": 5.0,
      "reviewText": "Muito bem feita! Ótima para guardar joias.",
      "reviewImages": [
        "https://images.unsplash.com/photo-1603570419983-7e865b2f1f19?w=300&h=200&fit=crop"
      ]
    }
  },
  {
    "id": 5,
    "title": "Cachecol em Tear Manual",
    "price": 65.0,
    "author": "Fernanda Lima",
    "description": "Cachecol de lã feito em tear manual com fios tingidos naturalmente.",
    "img": "bijuterias.jpg",
    "review": {
      "reviewer": "Bianca Lopes",
      "rating": 4.8,
      "reviewText": "Quentinho e com cores lindas. Recomendo!",
      "reviewImages": [
        "https://images.unsplash.com/photo-1629195866521-62dd86d90b4f?w=300&h=200&fit=crop",
        "https://images.unsplash.com/photo-1583939003579-730e3918a45a?w=300&h=200&fit=crop"
      ]
    }
  },
  {
    "id": 6,
    "title": "Tapete de Crochê Floral",
    "price": 98.5,
    "author": "Marina Oliveira",
    "description": "Tapete de crochê em formato floral, perfeito para decoração de interiores.",
    "img": "ceramica-e-porcelana.webp",
    "review": {
      "reviewer": "Renata Ferreira",
      "rating": 5.0,
      "reviewText": "Simplesmente apaixonada pelo tapete! Muito caprichado.",
      "reviewImages": [
        "https://images.unsplash.com/photo-1515562141207-7a88fb7ce338?w=300&h=200&fit=crop"
      ]
    }
  },
  {
    "id": 7,
    "title": "Tigela de Cerâmica Esmaltada",
    "price": 89.0,
    "author": "João Fernandes",
    "description": "Tigela artesanal de porcelana com acabamento esmaltado em azul cobalto.",
    "img": "ceramica-e-porcelana.webp",
    "review": {
      "reviewer": "Eduardo Melo",
      "rating": 5.0,
      "reviewText": "Excelente acabamento! A tigela é ainda mais bonita ao vivo.",
      "reviewImages": [
        "https://images.unsplash.com/photo-1583939003579-730e3918a45a?w=300&h=200&fit=crop"
      ]
    }
  },
  {
    "id": 8,
    "title": "Tigela de Cerâmica Esmaltada",
    "price": 89.0,
    "author": "João Fernandes",
    "description": "Tigela artesanal de porcelana com acabamento esmaltado em azul cobalto.",
    "img": "ceramica-e-porcelana.webp",
    "review": {
      "reviewer": "Eduardo Melo",
      "rating": 5.0,
      "reviewText": "Excelente acabamento! A tigela é ainda mais bonita ao vivo.",
      "reviewImages": [
        "https://images.unsplash.com/photo-1583939003579-730e3918a45a?w=300&h=200&fit=crop"
      ]
    }
  },
  {
    "id": 9,
    "title": "Tigela de Cerâmica Esmaltada",
    "price": 89.0,
    "author": "João Fernandes",
    "description": "Tigela artesanal de porcelana com acabamento esmaltado em azul cobalto.",
    "img": "ceramica-e-porcelana.webp",
    "review": {
      "reviewer": "Eduardo Melo",
      "rating": 5.0,
      "reviewText": "Excelente acabamento! A tigela é ainda mais bonita ao vivo.",
      "reviewImages": [
        "https://images.unsplash.com/photo-1583939003579-730e3918a45a?w=300&h=200&fit=crop"
      ]
    }
  },
  {
    "id": 10,
    "title": "Tigela de Cerâmica Esmaltada",
    "price": 89.0,
    "author": "João Fernandes",
    "description": "Tigela artesanal de porcelana com acabamento esmaltado em azul cobalto.",
    "img": "ceramica-e-porcelana.webp",
    "review": {
      "reviewer": "Eduardo Melo",
      "rating": 5.0,
      "reviewText": "Excelente acabamento! A tigela é ainda mais bonita ao vivo.",
      "reviewImages": [
        "https://images.unsplash.com/photo-1583939003579-730e3918a45a?w=300&h=200&fit=crop"
      ]
    }
  },
  {
    "id": 11,
    "title": "Tigela de Cerâmica Esmaltada",
    "price": 89.0,
    "author": "João Fernandes",
    "description": "Tigela artesanal de porcelana com acabamento esmaltado em azul cobalto.",
    "img": "ceramica-e-porcelana.webp",
    "review": {
      "reviewer": "Eduardo Melo",
      "rating": 5.0,
      "reviewText": "Excelente acabamento! A tigela é ainda mais bonita ao vivo.",
      "reviewImages": [
        "https://images.unsplash.com/photo-1583939003579-730e3918a45a?w=300&h=200&fit=crop"
      ]
    }
  },
  {
    "id": 12,
    "title": "Tigela de Cerâmica Esmaltada",
    "price": 89.0,
    "author": "João Fernandes",
    "description": "Tigela artesanal de porcelana com acabamento esmaltado em azul cobalto.",
    "img": "ceramica-e-porcelana.webp",
    "review": {
      "reviewer": "Eduardo Melo",
      "rating": 5.0,
      "reviewText": "Excelente acabamento! A tigela é ainda mais bonita ao vivo.",
      "reviewImages": [
        "https://images.unsplash.com/photo-1583939003579-730e3918a45a?w=300&h=200&fit=crop"
      ]
    }
  }
]
